{
  "50": {
    "value": "#edf0e9",
    "type": "color",
    "description": "Secondary accent \u2014 charcoal 50."
  },
  "100": {
    "value": "#dbe1d2",
    "type": "color",
    "description": "Secondary accent \u2014 charcoal 100."
  },
  "200": {
    "value": "#b7c4a5",
    "type": "color",
    "description": "Secondary accent \u2014 charcoal 200."
  },
  "300": {
    "value": "#94a679",
    "type": "color",
    "description": "Secondary accent \u2014 charcoal 300."
  },
  "400": {
    "value": "#70894c",
    "type": "color",
    "description": "Secondary accent \u2014 charcoal 400."
  },
  "500": {
    "value": "#4c6b1f",
    "type": "color",
    "description": "Secondary accent \u2014 charcoal 500."
  },
  "600": {
    "value": "#3d5619",
    "type": "color",
    "description": "Secondary accent \u2014 charcoal 600."
  },
  "700": {
    "value": "#2e4013",
    "type": "color",
    "description": "Secondary accent \u2014 charcoal 700."
  },
  "800": {
    "value": "#1e2b0c",
    "type": "color",
    "description": "Secondary accent \u2014 charcoal 800."
  },
  "900": {
    "value": "#0f1506",
    "type": "color",
    "description": "Secondary accent \u2014 charcoal 900."
  },
  "950": {
    "value": "#080b03",
    "type": "color",
    "description": "Secondary accent \u2014 charcoal 950."
  }
}
