{
  "tokens": {
    "includeAllComponents": true,
    "destinationPath": "./doc-site/static/zebkit",
    "assetFilePath": "/zebkit/",
    "basePreset": "default",
    "tokenPath": "./theme/zebkit-docs",
    "exportTokens": true,
    "splitMode": "combined",
    "outputFormats": ["JSON"],
    "writeVariantRegistry": true,
    "writeTokenLookup": true,
    "writeAllowedTokenTypes": true,
    "tokenLookupOutputPath": "./doc-site/static/zebkit/token-lookup.json",
    "overlays": [
      {
        "themeName": "apple",
        "tokenPath": "./theme/zebkit-hero-apple",
        "destinationPath": "./doc-site/static/zebkit/themes"
      },
      {
        "themeName": "material",
        "tokenPath": "./theme/zebkit-hero-material",
        "destinationPath": "./doc-site/static/zebkit/themes"
      },
      {
        "themeName": "atlassian",
        "tokenPath": "./theme/zebkit-hero-atlassian",
        "destinationPath": "./doc-site/static/zebkit/themes"
      },
      {
        "themeName": "carbon",
        "tokenPath": "./theme/zebkit-hero-carbon",
        "destinationPath": "./doc-site/static/zebkit/themes"
      },
      {
        "themeName": "uber",
        "tokenPath": "./theme/zebkit-hero-uber",
        "destinationPath": "./doc-site/static/zebkit/themes"
      },
      {
        "themeName": "fluent",
        "tokenPath": "./theme/zebkit-hero-fluent",
        "destinationPath": "./doc-site/static/zebkit/themes"
      }
    ],
    "tokens": { "fonts": { "strategy": "link" } }
  }
}
